column_reducer_dual.v
module column_reducer_dual (
    input  wire        clk,
    input  wire        rst,

    input  wire        num_valid,
    input  wire [31:0] num_in,

    input  wire        op_valid,
    input  wire        op_in,   // 0 = add, 1 = mul

    input  wire        done,

    output reg         result_valid,
    output reg  [63:0] result
);

    reg [63:0] sum_acc;
    reg [63:0] prod_acc;
    reg        started;
    reg        op;

    always @(posedge clk) begin
        if (rst) begin
            sum_acc      <= 0;
            prod_acc     <= 1;
            started      <= 0;
            op           <= 0;
            result       <= 0;
            result_valid <= 0;
        end else begin
            result_valid <= 0;

            if (op_valid)
                op <= op_in;

            if (num_valid) begin
                if (!started) begin
                    sum_acc  <= num_in;
                    prod_acc <= num_in;
                    started  <= 1;
                end else begin
                    sum_acc  <= sum_acc + num_in;
                    prod_acc <= prod_acc * num_in;
                end
            end

            if (done) begin
                result       <= (op) ? prod_acc : sum_acc;
                result_valid <= 1;

                // reset for next column
                sum_acc  <= 0;
                prod_acc <= 1;
                started  <= 0;
            end
        end
    end
endmodule

tb_column_reducer_dual.v
`timescale 1ns/1ps

module tb_column_reducer_dual;

    reg clk = 0;
    always #5 clk = ~clk;

    reg rst;
    reg num_valid;
    reg [31:0] num_in;
    reg op_valid;
    reg op_in;
    reg done;

    wire result_valid;
    wire [63:0] result;

    column_reducer_dual dut (
        .clk(clk),
        .rst(rst),
        .num_valid(num_valid),
        .num_in(num_in),
        .op_valid(op_valid),
        .op_in(op_in),
        .done(done),
        .result_valid(result_valid),
        .result(result)
    );

    initial begin
        $dumpfile("waves_dual.vcd");
        $dumpvars(0, tb_column_reducer_dual);

        rst = 1;
        num_valid = 0;
        op_valid  = 0;
        done      = 0;
        #20 rst = 0;

        // 123 * 45 * 6
        num_valid = 1; num_in = 123; #10;
        op_valid  = 1; op_in  = 1;   #10; op_valid = 0;

        num_in = 45; #10;
        num_in = 6;  #10;
        num_valid = 0;

        done = 1; #10;
        done = 0;

        #50;
        $finish;
    end
endmodule

waves_dual.vcd
$date
	Tue Jan 13 03:43:15 2026
$end
$version
	Icarus Verilog
$end
$timescale
	1ps
$end
$scope module tb_column_reducer_dual $end
$var wire 1 ! result_valid $end
$var wire 64 " result [63:0] $end
$var reg 1 # clk $end
$var reg 1 $ done $end
$var reg 32 % num_in [31:0] $end
$var reg 1 & num_valid $end
$var reg 1 ' op_in $end
$var reg 1 ( op_valid $end
$var reg 1 ) rst $end
$scope module dut $end
$var wire 1 # clk $end
$var wire 1 $ done $end
$var wire 32 * num_in [31:0] $end
$var wire 1 & num_valid $end
$var wire 1 ' op_in $end
$var wire 1 ( op_valid $end
$var wire 1 ) rst $end
$var reg 1 + op $end
$var reg 64 , prod_acc [63:0] $end
$var reg 64 - result [63:0] $end
$var reg 1 ! result_valid $end
$var reg 1 . started $end
$var reg 64 / sum_acc [63:0] $end
$upscope $end
$upscope $end
$enddefinitions $end
#0
$dumpvars
bx /
x.
bx -
bx ,
x+
bx *
1)
0(
x'
0&
bx %
0$
0#
bx "
x!
$end
#5000
0!
b0 "
b0 -
0+
0.
b1 ,
b0 /
1#
#10000
0#
#15000
1#
#20000
0#
b1111011 %
b1111011 *
1&
0)
#25000
1.
b1111011 ,
b1111011 /
1#
#30000
0#
1'
1(
#35000
b11101100011001 ,
b11110110 /
1+
1#
#40000
0#
b101101 %
b101101 *
0(
#45000
b10100110001101100101 ,
b100100011 /
1#
#50000
0#
b110 %
b110 *
#55000
b1111100101010001011110 ,
b100101001 /
1#
#60000
0#
1$
0&
#65000
0.
b1 ,
b0 /
1!
b1111100101010001011110 "
b1111100101010001011110 -
1#
#70000
0#
0$
#75000
0!
1#
